README.md
pyproject.toml
setup.py
astro_cloud/__init__.py
astro_cloud/constants.py
astro_cloud.egg-info/PKG-INFO
astro_cloud.egg-info/SOURCES.txt
astro_cloud.egg-info/dependency_links.txt
astro_cloud.egg-info/entry_points.txt
astro_cloud.egg-info/not-zip-safe
astro_cloud.egg-info/requires.txt
astro_cloud.egg-info/top_level.txt
astro_cloud/auth/__init__.py
astro_cloud/auth/aws.py
astro_cloud/auth/azure.py
astro_cloud/auth/digital_ocean.py
astro_cloud/auth/gcp.py
astro_cloud/fits/__init__.py
astro_cloud/fits/constants.py
astro_cloud/fits/datatypes.py
astro_cloud/fits/utils.py
astro_cloud/fits/index/__init__.py
astro_cloud/fits/index/aws.py
astro_cloud/fits/index/azure.py
astro_cloud/fits/index/base.py
astro_cloud/fits/index/digital_ocean.py
astro_cloud/fits/index/gcp.py
astro_cloud_tests/__init__.py
astro_cloud_tests/pytest_constants.py
astro_cloud_tests/pytest_datatypes.py
astro_cloud_tests/pytest_utils.py
astro_cloud_tests/auth/__init__.py
astro_cloud_tests/auth/test_aws.py
astro_cloud_tests/auth/test_azure.py
astro_cloud_tests/auth/test_digital_ocean.py
astro_cloud_tests/auth/test_gcp.py
astro_cloud_tests/fits/__init__.py
astro_cloud_tests/fits/test_utils.py
astro_cloud_tests/fits/index/__init__.py
astro_cloud_tests/fits/index/test_aws.py
astro_cloud_tests/fits/index/test_azure.py
astro_cloud_tests/fits/index/test_digital_ocean.py
astro_cloud_tests/fits/index/test_gcp.py