Metadata-Version: 2.1
Name: astro-cloud
Version: 0.0.1
Summary: A utility to make accessing static content in the cloud, efficient
Home-page: https://github.com/jbcurtin/astro-cloud
Author: Joseph Curtin <42@jbcurtin.io
Author-email: astro-cloud@jbcurtin.io
License: MIT
Platform: UNKNOWN
Classifier: Operating System :: OS Independent
Classifier: Programming Language :: Python
Classifier: Programming Language :: Python :: 3
Classifier: Programming Language :: Python :: 3.6
Classifier: Programming Language :: Python :: 3.7
Classifier: Programming Language :: Python :: 3.8
Classifier: Programming Language :: Python :: 3.9
Classifier: Programming Language :: Python :: 3 :: Only
Requires-Python: >=3.7
